pyrpio/__init__.py
pyrpio/gpio.py
pyrpio/i2c/__init__.py
pyrpio/i2c/ftdii2c.py
pyrpio/i2c/httpi2c.py
pyrpio/i2c/i2c.py
pyrpio/i2c/types.py
pyrpio/i2c_register_device.py
pyrpio/lib/bcm2835.c
pyrpio/lib/bcm2835.h
pyrpio/lib/bcm2835_ext.h
pyrpio/lib/mdio.c
pyrpio/lib/mdio.h
pyrpio/lib/mdio_ext.h
pyrpio/lib/module.c
pyrpio/mdio.py
pyrpio/pinmap.py
pyrpio/pwm.py
pyrpio/spi/__init__.py
pyrpio/spi/spi.py
pyrpio/spi/types.py
pyrpio/types.py
pyrpio-0.4.1.dist-info/LICENSE.md
pyrpio-0.4.1.dist-info/WHEEL
pyrpio-0.4.1.dist-info/METADATA
pyrpio-0.4.1.dist-info/RECORD
