Metadata-Version: 2.1
Name: pyrpio
Version: 0.4.1
Summary: Python-wrapped RPIO
Home-page: https://github.com/Samtec-ASH/pyrpio
License: MIT
Author: Adam Page
Author-email: adam.page@samtec.com
Requires-Python: >=3.7,<4.0
Classifier: License :: OSI Approved :: MIT License
Classifier: Programming Language :: Python :: 3
Classifier: Programming Language :: Python :: 3.7
Classifier: Programming Language :: Python :: 3.8
Classifier: Programming Language :: Python :: 3.9
Provides-Extra: ftdi
Provides-Extra: httpx
Requires-Dist: httpx (>=0.18.2,<0.19.0); extra == "httpx"
Requires-Dist: pyftdi (>=0.53.2,<0.54.0); extra == "ftdi"
Project-URL: Repository, https://github.com/Samtec-ASH/pyrpio
